bdbomdiff/__init__.py
bdbomdiff/template_aosd_new.xlsx
bdbomdiff-0.3.6.dist-info/entry_points.txt
bdbomdiff-0.3.6.dist-info/LICENSE
bdbomdiff-0.3.6.dist-info/WHEEL
bdbomdiff-0.3.6.dist-info/METADATA
bdbomdiff-0.3.6.dist-info/RECORD
