Metadata-Version: 2.1
Name: bdbomdiff
Version: 0.3.6
Summary: Blackduck BOM Diff to excel for AOSD import
License: MIT
Author: dineshr93gmail.com
Requires-Python: >=3.10,<4.0
Classifier: License :: OSI Approved :: MIT License
Classifier: Programming Language :: Python :: 3
Classifier: Programming Language :: Python :: 3.10
Requires-Dist: blackduck (>=1.0.7,<2.0.0)
Requires-Dist: importlib-resources (>=5.9.0,<6.0.0)
Requires-Dist: openpyxl (>=3.0.10,<4.0.0)
